[
	{"model": "fair_categories.division", "pk": 1, "fields": {"active": true, "short_description": "Middle School"}}, 
	{"model": "fair_categories.division", "pk": 2, "fields": {"active": true, "short_description": "High School"}}, 
	{"model": "fair_categories.category", "pk": 1, "fields": {"active": true, "short_description": "Physical Sciences"}}, 
	{"model": "fair_categories.category", "pk": 2, "fields": {"active": true, "short_description": "Life Sciences"}},
    {"model": "fair_categories.subcategory", "pk": 1, "fields": {"active": true, "abbreviation": "CHEM", "short_description": "Chemistry", "category": 1}}, 
    {"model": "fair_categories.subcategory", "pk": 2, "fields": {"active": true, "abbreviation": "EAEV", "short_description": "Earth and Environmental Sciences", "category": 1}}, 
    {"model": "fair_categories.subcategory", "pk": 3, "fields": {"active": true, "abbreviation": "EBED", "short_description": "Embedded Systems", "category": 1}}, 
    {"model": "fair_categories.subcategory", "pk": 4, "fields": {"active": true, "abbreviation": "EGCH", "short_description": "Energy: Chemical", "category": 1}}, 
    {"model": "fair_categories.subcategory", "pk": 5, "fields": {"active": true, "abbreviation": "EGPH", "short_description": "Energy: Physical", "category": 1}}, 
    {"model": "fair_categories.subcategory", "pk": 6, "fields": {"active": true, "abbreviation": "ENMC", "short_description": "Engineering Mechanics", "category": 1}}, 
    {"model": "fair_categories.subcategory", "pk": 7, "fields": {"active": true, "abbreviation": "ENEV", "short_description": "Environmental Engineering", "category": 1}}, 
    {"model": "fair_categories.subcategory", "pk": 8, "fields": {"active": true, "abbreviation": "MATS", "short_description": "Materials Science", "category": 1}}, 
    {"model": "fair_categories.subcategory", "pk": 9, "fields": {"active": true, "abbreviation": "MATH", "short_description": "Mathematics", "category": 1}}, 
    {"model": "fair_categories.subcategory", "pk": 10, "fields": {"active": true, "abbreviation": "PHYS", "short_description": "Physics and Astronomy", "category": 1}}, 
    {"model": "fair_categories.subcategory", "pk": 11, "fields": {"active": true, "abbreviation": "ROBO", "short_description": "Robotics and Intelligent Machines", "category": 1}}, 
    {"model": "fair_categories.subcategory", "pk": 12, "fields": {"active": true, "abbreviation": "SOFT", "short_description": "Systems Software", "category": 1}}, 
    {"model": "fair_categories.subcategory", "pk": 13, "fields": {"active": true, "abbreviation": "ANIM", "short_description": "Animal Sciences", "category": 2}}, 
    {"model": "fair_categories.subcategory", "pk": 14, "fields": {"active": true, "abbreviation": "BEHA", "short_description": "Behavioral and Social Sciences", "category": 2}}, 
    {"model": "fair_categories.subcategory", "pk": 15, "fields": {"active": true, "abbreviation": "BCHM", "short_description": "Biochemistry", "category": 2}}, 
    {"model": "fair_categories.subcategory", "pk": 16, "fields": {"active": true, "abbreviation": "BMED", "short_description": "Biomedical and Health Sciences", "category": 2}}, 
    {"model": "fair_categories.subcategory", "pk": 17, "fields": {"active": true, "abbreviation": "ENBM", "short_description": "Biomedical Engineering", "category": 2}}, 
    {"model": "fair_categories.subcategory", "pk": 18, "fields": {"active": true, "abbreviation": "CELL", "short_description": "Cellular and Molecular Biology", "category": 2}}, 
    {"model": "fair_categories.subcategory", "pk": 19, "fields": {"active": true, "abbreviation": "CBIO", "short_description": "Computational Biology and Bioinformatics", "category": 2}}, 
    {"model": "fair_categories.subcategory", "pk": 20, "fields": {"active": true, "abbreviation": "MCRO", "short_description": "Microbiology", "category": 2}}, 
    {"model": "fair_categories.subcategory", "pk": 21, "fields": {"active": true, "abbreviation": "PLNT", "short_description": "Plant Sciences", "category": 2}}, 
    {"model": "fair_categories.subcategory", "pk": 22, "fields": {"active": true, "abbreviation": "TMED", "short_description": "Translational Medical Sciences", "category": 2}}
]